unravel/__init__.py
unravel/__main__.py
unravel/cfg.py
unravel/continuity.py
unravel/core.py
unravel/dealias.py
unravel/debug.py
unravel/filtering.py
unravel/find_reference.py
unravel/initialisation.py
unravel/odim.py
unravel-1.4.0.dist-info/licenses/LICENSE
unravel-1.4.0.dist-info/METADATA
unravel-1.4.0.dist-info/WHEEL
unravel-1.4.0.dist-info/top_level.txt
unravel-1.4.0.dist-info/RECORD
