Metadata-Version: 2.4
Name: unravel
Version: 1.4.0
Summary: A dealiasing technique for Doppler radar velocity.
Author-email: Valentin Louf <valentin.louf@bom.gov.au>
License: Apache-2.0
Project-URL: Homepage, https://github.com/vlouf/dealias
Project-URL: Documentation, https://github.com/vlouf/dealias#readme
Project-URL: Repository, https://github.com/vlouf/dealias
Project-URL: Issues, https://github.com/vlouf/dealias/issues
Keywords: radar,weather,meteorology,dealiasing,Doppler
Classifier: Development Status :: 5 - Production/Stable
Classifier: Intended Audience :: Science/Research
Classifier: Topic :: Scientific/Engineering :: Atmospheric Science
Classifier: Programming Language :: Python :: 3.9
Classifier: Programming Language :: Python :: 3.10
Classifier: Programming Language :: Python :: 3.11
Classifier: Programming Language :: Python :: 3.12
Classifier: Programming Language :: Python :: 3.13
Requires-Python: >=3.8
License-File: LICENSE
Requires-Dist: numba
Requires-Dist: numpy
Requires-Dist: xarray
Requires-Dist: pyodim
Requires-Dist: dask
Requires-Dist: arm_pyart
Provides-Extra: dev
Requires-Dist: pytest>=7.0; extra == "dev"
Requires-Dist: pytest-cov>=4.0; extra == "dev"
Requires-Dist: pytest-xdist; extra == "dev"
Requires-Dist: black>=24.0; extra == "dev"
Requires-Dist: flake8>=7.0; extra == "dev"
Requires-Dist: isort>=5.13; extra == "dev"
Requires-Dist: pre-commit>=3.0; extra == "dev"
Dynamic: license-file
